cis_checks_1/__init__.py
cis_checks_1/iam_control_1.py
cis_checks_1/logging_control_2.py
cis_checks_1/monitoring_control_3.py
cis_checks_1/networking_control_4.py
cis_checks_1/security_control_5.py
cis_checks_1/utils.py
cis_checks_1-0.0.2.dist-info/METADATA
cis_checks_1-0.0.2.dist-info/WHEEL
cis_checks_1-0.0.2.dist-info/top_level.txt
cis_checks_1-0.0.2.dist-info/RECORD
